pygrad/__init__.py
pygrad/core.py
pygrad/data.py
pygrad/exceptions.py
pygrad/functions.py
pygrad/utils.py
pygrad/nn/__init__.py
pygrad/nn/module.py
pygrad/nn/optim.py
pygrad-0.1.0.dist-info/LICENSE
pygrad-0.1.0.dist-info/METADATA
pygrad-0.1.0.dist-info/WHEEL
pygrad-0.1.0.dist-info/top_level.txt
pygrad-0.1.0.dist-info/RECORD
