Metadata-Version: 2.1
Name: pygrad
Version: 0.1.0
Summary: A pure Python autograd library
Home-page: https://github.com/jaketae/pygrad
Author: Jake Tae
Author-email: jaesungtae@gmail.com
License: UNKNOWN
Platform: UNKNOWN
Classifier: Programming Language :: Python :: 3
Classifier: Programming Language :: Python :: 3.6
Classifier: Programming Language :: Python :: 3.7
Classifier: Programming Language :: Python :: 3.8
Classifier: License :: OSI Approved :: MIT License
Classifier: Operating System :: OS Independent
Requires-Python: >=3.6
Requires-Dist: numpy
Requires-Dist: matplotlib
